upsunvalidator/__init__.py
upsunvalidator/__main__.py
upsunvalidator/_version.py
upsunvalidator/examples/__init__.py
upsunvalidator/examples/meta.yaml
upsunvalidator/examples/akeneo/.upsun/config.yaml
upsunvalidator/examples/directus/.upsun/config.yaml
upsunvalidator/examples/django-pgvector/.upsun/config.yaml
upsunvalidator/examples/django-redis-celery/.upsun/config.yaml
upsunvalidator/examples/django4/.upsun/config.yaml
upsunvalidator/examples/drupal10/.upsun/config.yaml
upsunvalidator/examples/drupal11/.upsun/config.yaml
upsunvalidator/examples/express/.upsun/config.yaml
upsunvalidator/examples/fastapi/.upsun/config.yaml
upsunvalidator/examples/flask/.upsun/config.yaml
upsunvalidator/examples/gatsby/.upsun/config.yaml
upsunvalidator/examples/gatsby-wordpress/.upsun/config.yaml
upsunvalidator/examples/hugo/.upsun/config.yaml
upsunvalidator/examples/laravel/.upsun/config.yaml
upsunvalidator/examples/magentoce/.upsun/config.yaml
upsunvalidator/examples/nextjs/.upsun/config.yaml
upsunvalidator/examples/nuxtjs/.upsun/config.yaml
upsunvalidator/examples/pimcore/.upsun/config.yaml
upsunvalidator/examples/pyramid/.upsun/config.yaml
upsunvalidator/examples/rails/.upsun/config.yaml
upsunvalidator/examples/shopware/.upsun/config.yaml
upsunvalidator/examples/strapi4/.upsun/config.yaml
upsunvalidator/examples/sylius/.upsun/config.yaml
upsunvalidator/examples/typo3-v11/.upsun/config.yaml
upsunvalidator/examples/wagtail/.upsun/config.yaml
upsunvalidator/examples/wordpress-bedrock/.upsun/config.yaml
upsunvalidator/examples/wordpress-composer/.upsun/config.yaml
upsunvalidator/examples/wordpress-vanilla/.upsun/config.yaml
upsunvalidator/schemas/__init__.py
upsunvalidator/schemas/extensions.py
upsunvalidator/schemas/services.py
upsunvalidator/schemas/upsun.py
upsunvalidator/schemas/data/extensions/php_extensions.yaml
upsunvalidator/schemas/data/providers/upsun.json
upsunvalidator/schemas/data/services/registry.json
upsunvalidator/schemas/data/services/stacks.json
upsunvalidator-0.3.2.dist-info/licenses/LICENSE
upsunvalidator-0.3.2.dist-info/METADATA
upsunvalidator-0.3.2.dist-info/WHEEL
upsunvalidator-0.3.2.dist-info/entry_points.txt
upsunvalidator-0.3.2.dist-info/top_level.txt
upsunvalidator-0.3.2.dist-info/RECORD
