Metadata-Version: 2.4
Name: upsunvalidator
Version: 0.3.2
Summary: Validation library for Upsun Configuration
Author-email: "Jeck.ai" <robert@jeck.ai>
License: MIT
Project-URL: Home, https://jeck.ai
Project-URL: Source, https://github.com/Jeck-ai/upsunvalidator
Requires-Python: >=3.12
License-File: LICENSE
Requires-Dist: pyyaml
Requires-Dist: jsonschema
Requires-Dist: ruamel.yaml
Requires-Dist: pytest
Requires-Dist: click
Requires-Dist: click-extra
Dynamic: license-file
